recipeminecraft.py
minecraft_parser_table_von23334-0.0.2.dist-info/licenses/LICENSE.txt
minecraft_parser_table_von23334-0.0.2.dist-info/METADATA
minecraft_parser_table_von23334-0.0.2.dist-info/WHEEL
minecraft_parser_table_von23334-0.0.2.dist-info/top_level.txt
minecraft_parser_table_von23334-0.0.2.dist-info/RECORD
